shutils/__init__.py
shutils/cache.py
shutils/imagesize.py
shutils/param.py
shutils/rate_limiter.py
shutils/rwlock.py
shutils/utils.py
shutils/dag/__init__.py
shutils/dag/context.py
shutils/dag/context_queue.py
shutils/dag/dag.py
shutils/dag/data_white_board.py
shutils/dag/executor.py
shutils/dag/global_data.py
shutils/dag/helper.py
shutils/dag/limiter.py
shutils/dag/runtime.py
shutils/dag/serve_executor.py
shutils/dag/smart_lock.py
shutils/dag/task.py
shutils/dag/task_executor.py
shutils/dag/task_queue.py
shutils/dag/task_state.py
shutils/dag/utils.py
shutils/dag/visualizer.py
shutilspy-0.1.0.dist-info/METADATA
shutilspy-0.1.0.dist-info/WHEEL
shutilspy-0.1.0.dist-info/top_level.txt
shutilspy-0.1.0.dist-info/RECORD
