Metadata-Version: 2.4
Name: shutilspy
Version: 0.1.0
Summary: common python utils
Author-email: shlll <shlll7347@gmail.com>
Requires-Python: >=3.7
Requires-Dist: janus
Requires-Dist: flask
